chit/__init__.py
chit/chit.py
chit/config.py
chit/images.py
chit/import_claude.py
chit/utils.py
chitgpt-1.29.0.dist-info/METADATA
chitgpt-1.29.0.dist-info/WHEEL
chitgpt-1.29.0.dist-info/top_level.txt
chitgpt-1.29.0.dist-info/RECORD
