Metadata-Version: 2.4
Name: chitgpt
Version: 1.29.0
Summary: git-like system for llm chats
Requires-Python: >=3.10
Requires-Dist: ipykernel>=6.29.5
Requires-Dist: ipython>=8.32.0
Requires-Dist: ipywidgets>=8.1.5
Requires-Dist: litellm>=1.63.11
Requires-Dist: nbformat>=5.10.4
Requires-Dist: numpydoc>=1.8.0
Requires-Dist: pillow>=11.1.0
